{"Name":{"0133.HK":"CHINA MERCHANTS"},"Exchange":{"0133.HK":"HKG"},"Price":{"0133.HK":8.26},"Price_currency":{"0133.HK":"HKD"},"Shares":{"0133.HK":152332992},"Reporting_Currency":{"0133.HK":"USD"},"Fx_rate":{"0133.HK":7.813371266},"Dividend":{"0133.HK":0.0800000108},"Last_fy":{"0133.HK":1640908800000},"TotalAssets":{"0133.HK":873476735.0},"CurrentAssets":{"0133.HK":0.0},"CurrentLiabilities":{"0133.HK":0.0},"CurrentDebtAndCapitalLeaseObligation":{"0133.HK":0.0},"CurrentCapitalLeaseObligation":{"0133.HK":0.0},"LongTermDebtAndCapitalLeaseObligation":{"0133.HK":0.0},"LongTermCapitalLeaseObligation":{"0133.HK":0.0},"TotalEquityGrossMinorityInterest":{"0133.HK":679578520.0},"MinorityInterest":{"0133.HK":0.0},"CashAndCashEquivalents":{"0133.HK":43512652.0},"OtherShortTermInvestments":{"0133.HK":0.0},"InvestmentProperties":{"0133.HK":0.0},"LongTermEquityInvestment":{"0133.HK":0.0},"InvestmentinFinancialAssets":{"0133.HK":0.0},"NetPPE":{"0133.HK":0.0},"TotalRevenue":{"0133.HK":62995503.0},"CostOfRevenue":{"0133.HK":0.0},"SellingGeneralAndAdministration":{"0133.HK":19974735.0},"InterestExpense":{"0133.HK":0.0},"NetIncomeCommonStockholders":{"0133.HK":24205367.0}}