{"Name":{"0336.HK":"HUABAO INTL"},"Exchange":{"0336.HK":"HKG"},"Price":{"0336.HK":4.1},"Price_currency":{"0336.HK":"HKD"},"Shares":{"0336.HK":3229929984},"Reporting_Currency":{"0336.HK":"CNY"},"Fx_rate":{"0336.HK":1.1307796824},"Dividend":{"0336.HK":0.0},"Last_fy":{"0336.HK":1640908800000},"TotalAssets":{"0336.HK":17102003000.0},"CurrentAssets":{"0336.HK":8328642000.0},"CurrentLiabilities":{"0336.HK":1429199000.0},"CurrentDebtAndCapitalLeaseObligation":{"0336.HK":531261000.0},"CurrentCapitalLeaseObligation":{"0336.HK":24252000.0},"LongTermDebtAndCapitalLeaseObligation":{"0336.HK":22511000.0},"LongTermCapitalLeaseObligation":{"0336.HK":22511000.0},"TotalEquityGrossMinorityInterest":{"0336.HK":15382712000.0},"MinorityInterest":{"0336.HK":0.0},"CashAndCashEquivalents":{"0336.HK":4062331000.0},"OtherShortTermInvestments":{"0336.HK":1902210000.0},"InvestmentProperties":{"0336.HK":0.0},"LongTermEquityInvestment":{"0336.HK":851373000.0},"InvestmentinFinancialAssets":{"0336.HK":220030000.0},"NetPPE":{"0336.HK":2283160000.0},"TotalRevenue":{"0336.HK":3882683000.0},"CostOfRevenue":{"0336.HK":1586021000.0},"SellingGeneralAndAdministration":{"0336.HK":1133907000.0},"InterestExpense":{"0336.HK":81468000.0},"NetIncomeCommonStockholders":{"0336.HK":675131000.0}}