{"Name":{"1483.HK":"NET-A-GO TECH"},"Exchange":{"1483.HK":"HKG"},"Price":{"1483.HK":1.1},"Price_currency":{"1483.HK":"HKD"},"Shares":{"1483.HK":795000000},"Reporting_Currency":{"1483.HK":"HKD"},"Fx_rate":{"1483.HK":1},"Dividend":{"1483.HK":0.0},"Last_fy":{"1483.HK":1640908800000},"TotalAssets":{"1483.HK":845292000.0},"CurrentAssets":{"1483.HK":511236000.0},"CurrentLiabilities":{"1483.HK":160252000.0},"CurrentDebtAndCapitalLeaseObligation":{"1483.HK":13897000.0},"CurrentCapitalLeaseObligation":{"1483.HK":609000.0},"LongTermDebtAndCapitalLeaseObligation":{"1483.HK":3340000.0},"LongTermCapitalLeaseObligation":{"1483.HK":3340000.0},"TotalEquityGrossMinorityInterest":{"1483.HK":642211000.0},"MinorityInterest":{"1483.HK":0.0},"CashAndCashEquivalents":{"1483.HK":231341000.0},"OtherShortTermInvestments":{"1483.HK":68928000.0},"InvestmentProperties":{"1483.HK":98816000.0},"LongTermEquityInvestment":{"1483.HK":0.0},"InvestmentinFinancialAssets":{"1483.HK":0.0},"NetPPE":{"1483.HK":58387000.0},"TotalRevenue":{"1483.HK":332047000.0},"CostOfRevenue":{"1483.HK":250195000.0},"SellingGeneralAndAdministration":{"1483.HK":71434000.0},"InterestExpense":{"1483.HK":64000.0},"NetIncomeCommonStockholders":{"1483.HK":37615000.0}}