{"1640908800000":{"Ticker":"1502.HK","Name":"FIN STREET PPT","Exchange":"HKG","Price":2.8,"Price_currency":"HKD","Shares":103500000,"Reporting_Currency":"CNY","Fx_rate":1.1307796824,"Dividend":0.0,"Last_fy":1640908800000,"TotalAssets":1924413000.0,"CurrentAssets":1793758000.0,"CurrentLiabilities":739426000.0,"CurrentDebtAndCapitalLeaseObligation":22644000.0,"CurrentCapitalLeaseObligation":22644000.0,"LongTermDebtAndCapitalLeaseObligation":28748000.0,"LongTermCapitalLeaseObligation":28748000.0,"TotalEquityGrossMinorityInterest":1150739000.0,"MinorityInterest":0.0,"CashAndCashEquivalents":1361711000.0,"OtherShortTermInvestments":23741000.0,"InvestmentProperties":9662000.0,"LongTermEquityInvestment":15273000.0,"InvestmentinFinancialAssets":0.0,"NetPPE":76717000.0,"TotalRevenue":1320480000.0,"CostOfRevenue":1057745000.0,"SellingGeneralAndAdministration":82226000.0,"InterestExpense":2358000.0,"NetIncomeCommonStockholders":137717000.0}}