{"Name":{"3818.HK":"CHINA DONGXIANG"},"Exchange":{"3818.HK":"HKG"},"Price":{"3818.HK":0.355},"Price_currency":{"3818.HK":"HKD"},"Shares":{"3818.HK":5887560192},"Reporting_Currency":{"3818.HK":"CNY"},"Fx_rate":{"3818.HK":1.1307796824},"Dividend":{"3818.HK":0.0},"Last_fy":{"3818.HK":1648684800000},"TotalAssets":{"3818.HK":10356791000.0},"CurrentAssets":{"3818.HK":4892034000.0},"CurrentLiabilities":{"3818.HK":676680000.0},"CurrentDebtAndCapitalLeaseObligation":{"3818.HK":83700000.0},"CurrentCapitalLeaseObligation":{"3818.HK":42551000.0},"LongTermDebtAndCapitalLeaseObligation":{"3818.HK":22873000.0},"LongTermCapitalLeaseObligation":{"3818.HK":22873000.0},"TotalEquityGrossMinorityInterest":{"3818.HK":9354131000.0},"MinorityInterest":{"3818.HK":0.0},"CashAndCashEquivalents":{"3818.HK":2602990000.0},"OtherShortTermInvestments":{"3818.HK":1300952000.0},"InvestmentProperties":{"3818.HK":0.0},"LongTermEquityInvestment":{"3818.HK":18164000.0},"InvestmentinFinancialAssets":{"3818.HK":4284077000.0},"NetPPE":{"3818.HK":215965000.0},"TotalRevenue":{"3818.HK":1915735000.0},"CostOfRevenue":{"3818.HK":793560000.0},"SellingGeneralAndAdministration":{"3818.HK":1375234000.0},"InterestExpense":{"3818.HK":11387000.0},"NetIncomeCommonStockholders":{"3818.HK":-1746944000.0}}