{"1640908800000":{"Ticker":"0576.HK","Name":"ZHEJIANGEXPRESS","Exchange":"HKG","Price":6.31,"Price_currency":"HKD","Shares":1433849984,"Reporting_Currency":"CNY","Fx_rate":1.1382608092,"Dividend":0.0,"Buyback":0.0,"Last_fy":1640908800000,"TotalAssets":176671853000.0,"CurrentAssets":132729646000.0,"CurrentLiabilities":89986063000.0,"CurrentDebtAndCapitalLeaseObligation":14011204000.0,"CurrentCapitalLeaseObligation":140704000.0,"LongTermDebtAndCapitalLeaseObligation":40333258000.0,"LongTermCapitalLeaseObligation":305611000.0,"TotalEquityGrossMinorityInterest":45880241000.0,"MinorityInterest":0.0,"CashAndCashEquivalents":23227639000.0,"OtherShortTermInvestments":46691112000.0,"InvestmentProperties":0.0,"LongTermEquityInvestment":10339231000.0,"InvestmentinFinancialAssets":262266000.0,"NetPPE":5438739000.0,"TotalRevenue":16262601000.0,"CostOfRevenue":9521482000.0,"SellingGeneralAndAdministration":173447000.0,"InterestExpense":1942533000.0,"NetIncomeCommonStockholders":4762431000.0,"GrossMargin":58.55,"EBIT":6567672000.0,"EbitMargin":40.39,"NetMargin":29.28,"Avg_Gross_margin":58.53,"Avg_sales_growth":18.03,"Avg_ebit_margin":40.3466666667,"Avg_ebit_growth":16.77,"Avg_net_margin":28.4733333333,"Avg_NetIncome_growth":19.83,"Years_of_data":3}}