{"1640908800000":{"Ticker":"0952.HK","Name":"TONGHAI FIN","Exchange":"HKG","Price":0.18,"Price_currency":"HKD","Shares":6197049856,"Reporting_Currency":"HKD","Fx_rate":1,"Dividend":0.0,"Buyback":0.0001234458,"Last_fy":1640908800000,"TotalAssets":6131188000.0,"CurrentAssets":5854572000.0,"CurrentLiabilities":2780123000.0,"CurrentDebtAndCapitalLeaseObligation":1188213000.0,"CurrentCapitalLeaseObligation":29198000.0,"LongTermDebtAndCapitalLeaseObligation":852000.0,"LongTermCapitalLeaseObligation":852000.0,"TotalEquityGrossMinorityInterest":3349766000.0,"MinorityInterest":0.0,"CashAndCashEquivalents":213695000.0,"OtherShortTermInvestments":1137690000.0,"InvestmentProperties":0.0,"LongTermEquityInvestment":2188000.0,"InvestmentinFinancialAssets":67428000.0,"NetPPE":52459000.0,"TotalRevenue":857822000.0,"CostOfRevenue":328016000.0,"SellingGeneralAndAdministration":36911000.0,"InterestExpense":62442000.0,"NetIncomeCommonStockholders":-2260577000.0,"GrossMargin":38.24,"EBIT":492895000.0,"EbitMargin":57.46,"NetMargin":-263.53,"Avg_Gross_margin":41.49,"Avg_sales_growth":9.69,"Avg_ebit_margin":56.0066666667,"Avg_ebit_growth":18.17,"Avg_net_margin":-84.4966666667,"Avg_NetIncome_growth":-229.22,"Years_of_data":3}}