{"1640908800000":{"Ticker":"0990.HK","Name":"THEME INT'L","Exchange":"HKG","Price":0.76,"Price_currency":"HKD","Shares":13471299584,"Reporting_Currency":"HKD","Fx_rate":1,"Dividend":0.0,"Buyback":0.0,"Last_fy":1640908800000,"TotalAssets":12220020000.0,"CurrentAssets":11687606000.0,"CurrentLiabilities":7025114000.0,"CurrentDebtAndCapitalLeaseObligation":257410000.0,"CurrentCapitalLeaseObligation":4045000.0,"LongTermDebtAndCapitalLeaseObligation":0.0,"LongTermCapitalLeaseObligation":0.0,"TotalEquityGrossMinorityInterest":5178207000.0,"MinorityInterest":0.0,"CashAndCashEquivalents":2815641000.0,"OtherShortTermInvestments":16620000.0,"InvestmentProperties":6665000.0,"LongTermEquityInvestment":244303000.0,"InvestmentinFinancialAssets":21544000.0,"NetPPE":221957000.0,"TotalRevenue":34644900000.0,"CostOfRevenue":33175881000.0,"SellingGeneralAndAdministration":227265000.0,"InterestExpense":5373000.0,"NetIncomeCommonStockholders":997967000.0,"GrossMargin":95.76,"EBIT":1241754000.0,"EbitMargin":3.58,"NetMargin":2.88,"Avg_Gross_margin":95.7733333333,"Avg_sales_growth":79.19,"Avg_ebit_margin":3.21,"Avg_ebit_growth":100.25,"Avg_net_margin":2.32,"Avg_NetIncome_growth":164.88,"Years_of_data":3}}