{"1640908800000":{"Ticker":"3389.HK","Name":"HENGDELI","Exchange":"HKG","Price":0.217,"Price_currency":"HKD","Shares":4404020224,"Reporting_Currency":"CNY","Fx_rate":1.151104127,"Dividend":0.0,"Buyback":0.0113164785,"Last_fy":1640908800000,"TotalAssets":3512444000.0,"CurrentAssets":2255850000.0,"CurrentLiabilities":201647000.0,"CurrentDebtAndCapitalLeaseObligation":63676000.0,"CurrentCapitalLeaseObligation":11891000.0,"LongTermDebtAndCapitalLeaseObligation":31937000.0,"LongTermCapitalLeaseObligation":6379000.0,"TotalEquityGrossMinorityInterest":3278416000.0,"MinorityInterest":0.0,"CashAndCashEquivalents":1021392000.0,"OtherShortTermInvestments":34377000.0,"InvestmentProperties":128535000.0,"LongTermEquityInvestment":106985000.0,"InvestmentinFinancialAssets":455859000.0,"NetPPE":508986000.0,"TotalRevenue":992962000.0,"CostOfRevenue":879095000.0,"SellingGeneralAndAdministration":183614000.0,"InterestExpense":3109000.0,"NetIncomeCommonStockholders":26282000.0,"GrossMargin":88.53,"EBIT":-69747000.0,"EbitMargin":-7.02,"NetMargin":2.65,"Avg_Gross_margin":94.84,"Avg_sales_growth":-34.07,"Avg_ebit_margin":-14.8533333333,"Avg_ebit_growth":531.62,"Avg_net_margin":-14.17,"Avg_NetIncome_growth":-45.83,"Years_of_data":3}}