{"1640908800000":{"Ticker":"3396.HK","Name":"LEGENDHOLDING","Exchange":"HKG","Price":9.2,"Price_currency":"HKD","Shares":1271849984,"Reporting_Currency":"CNY","Fx_rate":1.1382608092,"Dividend":0.0,"Buyback":1.2913291824,"Last_fy":1640908800000,"TotalAssets":694488563000.0,"CurrentAssets":364742868000.0,"CurrentLiabilities":456259448000.0,"CurrentDebtAndCapitalLeaseObligation":46889492000.0,"CurrentCapitalLeaseObligation":1236375000.0,"LongTermDebtAndCapitalLeaseObligation":84072872000.0,"LongTermCapitalLeaseObligation":2679169000.0,"TotalEquityGrossMinorityInterest":100902267000.0,"MinorityInterest":0.0,"CashAndCashEquivalents":89934474000.0,"OtherShortTermInvestments":28440473000.0,"InvestmentProperties":12729387000.0,"LongTermEquityInvestment":16672586000.0,"InvestmentinFinancialAssets":39693788000.0,"NetPPE":35844531000.0,"TotalRevenue":489871677000.0,"CostOfRevenue":403940867000.0,"SellingGeneralAndAdministration":64231991000.0,"InterestExpense":5028205000.0,"NetIncomeCommonStockholders":5754886000.0,"GrossMargin":82.46,"EBIT":21698819000.0,"EbitMargin":4.43,"NetMargin":1.17,"Avg_Gross_margin":82.6566666667,"Avg_sales_growth":12.3,"Avg_ebit_margin":3.7733333333,"Avg_ebit_growth":27.72,"Avg_net_margin":1.01,"Avg_NetIncome_growth":28.01,"Years_of_data":3}}