{"1640908800000":{"Ticker":"6686.HK","Name":"NOAH HOLDINGS","Exchange":"HKG","Price":259.8,"Price_currency":"HKD","Shares":31189200,"Reporting_Currency":"CNY","Fx_rate":1.1382608092,"Dividend":0.0,"Buyback":11.9392610263,"Last_fy":1640908800000,"TotalAssets":11015048000.0,"CurrentAssets":5592947000.0,"CurrentLiabilities":1721315000.0,"CurrentDebtAndCapitalLeaseObligation":0.0,"CurrentCapitalLeaseObligation":0.0,"LongTermDebtAndCapitalLeaseObligation":95995000.0,"LongTermCapitalLeaseObligation":95995000.0,"TotalEquityGrossMinorityInterest":8878163000.0,"MinorityInterest":0.0,"CashAndCashEquivalents":3608044000.0,"OtherShortTermInvestments":85889000.0,"InvestmentProperties":0.0,"LongTermEquityInvestment":1510503000.0,"InvestmentinFinancialAssets":0.0,"NetPPE":2704055000.0,"TotalRevenue":4293094000.0,"CostOfRevenue":2168880000.0,"SellingGeneralAndAdministration":820452000.0,"InterestExpense":0.0,"NetIncomeCommonStockholders":1314131000.0,"GrossMargin":50.52,"EBIT":1303762000.0,"EbitMargin":30.37,"NetMargin":30.61,"Avg_Gross_margin":47.8366666667,"Avg_sales_growth":13.66,"Avg_ebit_margin":34.0833333333,"Avg_ebit_growth":6.35,"Avg_net_margin":10.84,"Avg_NetIncome_growth":-233.11,"Years_of_data":3}}