{"1640908800000":{"Ticker":"6908.HK","Name":"HG SEMI","Exchange":"HKG","Price":2.94,"Price_currency":"HKD","Shares":581601024,"Reporting_Currency":"CNY","Fx_rate":1.151104127,"Dividend":0.0,"Buyback":0.0,"Last_fy":1640908800000,"TotalAssets":636619000.0,"CurrentAssets":238582000.0,"CurrentLiabilities":45581000.0,"CurrentDebtAndCapitalLeaseObligation":17103000.0,"CurrentCapitalLeaseObligation":7103000.0,"LongTermDebtAndCapitalLeaseObligation":14739000.0,"LongTermCapitalLeaseObligation":14739000.0,"TotalEquityGrossMinorityInterest":576299000.0,"MinorityInterest":0.0,"CashAndCashEquivalents":35722000.0,"OtherShortTermInvestments":32994000.0,"InvestmentProperties":0.0,"LongTermEquityInvestment":0.0,"InvestmentinFinancialAssets":194238000.0,"NetPPE":137474000.0,"TotalRevenue":126137000.0,"CostOfRevenue":100630000.0,"SellingGeneralAndAdministration":100864000.0,"InterestExpense":1147000.0,"NetIncomeCommonStockholders":-446826000.0,"GrossMargin":79.78,"EBIT":-75357000.0,"EbitMargin":-59.74,"NetMargin":-354.24,"Avg_Gross_margin":77.7966666667,"Avg_sales_growth":-23.23,"Avg_ebit_margin":-14.4866666667,"Avg_ebit_growth":-575.39,"Avg_net_margin":-114.4666666667,"Avg_NetIncome_growth":-4982.98,"Years_of_data":3}}