{"1640908800000":{"Ticker":"9995.HK","Name":"REMEGEN-B","Exchange":"HKG","Price":60.95,"Price_currency":"HKD","Shares":489836992,"Reporting_Currency":"CNY","Fx_rate":1.1382608092,"Dividend":0.0,"Buyback":0.0,"Last_fy":1640908800000,"TotalAssets":6109215000.0,"CurrentAssets":4004839000.0,"CurrentLiabilities":564155000.0,"CurrentDebtAndCapitalLeaseObligation":35357000.0,"CurrentCapitalLeaseObligation":35357000.0,"LongTermDebtAndCapitalLeaseObligation":52705000.0,"LongTermCapitalLeaseObligation":52705000.0,"TotalEquityGrossMinorityInterest":5446604000.0,"MinorityInterest":0.0,"CashAndCashEquivalents":2589962000.0,"OtherShortTermInvestments":552761000.0,"InvestmentProperties":0.0,"LongTermEquityInvestment":0.0,"InvestmentinFinancialAssets":12067000.0,"NetPPE":2074846000.0,"TotalRevenue":1423902000.0,"CostOfRevenue":67163000.0,"SellingGeneralAndAdministration":482807000.0,"InterestExpense":5323000.0,"NetIncomeCommonStockholders":276258000.0,"GrossMargin":4.72,"EBIT":873932000.0,"EbitMargin":61.38,"NetMargin":19.4,"Avg_Gross_margin":4.72,"Avg_sales_growth":null,"Avg_ebit_margin":null,"Avg_ebit_growth":81.27,"Avg_net_margin":null,"Avg_NetIncome_growth":-38.71,"Years_of_data":3}}